hudsonthames_sphinx_theme/__init__.py
hudsonthames_sphinx_theme/layout.html
hudsonthames_sphinx_theme/theme.conf
hudsonthames_sphinx_theme/static/css/style.css
hudsonthames_sphinx_theme/static/css/top_bar.css
hudsonthames_sphinx_theme/static/images/logo_horisontal_white_teal.png
hudsonthames_sphinx_theme-0.1.5.dist-info/LICENSE.txt
hudsonthames_sphinx_theme-0.1.5.dist-info/METADATA
hudsonthames_sphinx_theme-0.1.5.dist-info/WHEEL
hudsonthames_sphinx_theme-0.1.5.dist-info/entry_points.txt
hudsonthames_sphinx_theme-0.1.5.dist-info/top_level.txt
hudsonthames_sphinx_theme-0.1.5.dist-info/RECORD
