Metadata-Version: 2.1
Name: hudsonthames-sphinx-theme
Version: 0.1.5
Summary: Hudson and Thames theme for Sphinx
Home-page: https://github.com/hudson-and-thames/hudsonthames_sphinx_theme
Author: Hudson and Thames Quantitative Research Limited
Author-email: research@hudsonthames.org
License: All Rights Reserved
Project-URL: Source, https://github.com/hudson-and-thames/hudsonthames_sphinx_theme
Project-URL: Bug Reports, https://github.com/hudson-and-thames/hudsonthames_sphinx_theme/issues
Project-URL: Project Boards, https://github.com/orgs/hudson-and-thames/projects
Project-URL: Blog, https://hudsonthames.org/blog/
Project-URL: Apprenticeship Program, https://hudsonthames.org/apprenticeship-program/
Platform: UNKNOWN
Classifier: Development Status :: 3 - Alpha
Classifier: Intended Audience :: Developers
Classifier: License :: Other/Proprietary License
Classifier: Operating System :: OS Independent
Classifier: Programming Language :: Python :: 3
Classifier: Programming Language :: Python :: 3.8
Classifier: Framework :: Sphinx
Classifier: Framework :: Sphinx :: Theme
Classifier: Environment :: Console
Classifier: Environment :: Web Environment
Classifier: Topic :: Documentation
Classifier: Topic :: Software Development :: Documentation
